{
  "date": "2026-04-19",
  "total_events": 5,
  "by_company": {
    "nippon_steel": {
      "count": 1,
      "sentiment_avg": 0.0
    },
    "posco": {
      "count": 1,
      "sentiment_avg": 0.0
    },
    "bridgestone": {
      "count": 1,
      "sentiment_avg": 0.0
    },
    "cheng_shin": {
      "count": 1,
      "sentiment_avg": 0.0
    },
    "hyundai": {
      "count": 1,
      "sentiment_avg": 0.0
    }
  },
  "by_topic": {
    "earnings": {
      "count": 5,
      "sentiment_avg": 0.0
    }
  },
  "baselines_used": {
    "companies": {},
    "topics": {}
  },
  "supply_chain_activity": []
}